beefore/__init__.py
beefore/__main__.py
beefore/command.py
beefore/diff.py
beefore/github.py
beefore/local.py
beefore/checks/__init__.py
beefore/checks/dco.py
beefore/checks/eslint.py
beefore/checks/javacheckstyle.py
beefore/checks/pycodestyle.py
beefore-0.2.4.dist-info/AUTHORS
beefore-0.2.4.dist-info/LICENSE
beefore-0.2.4.dist-info/METADATA
beefore-0.2.4.dist-info/WHEEL
beefore-0.2.4.dist-info/entry_points.txt
beefore-0.2.4.dist-info/top_level.txt
beefore-0.2.4.dist-info/RECORD
