Metadata-Version: 2.1
Name: beefore
Version: 0.2.4
Summary: Performs pre-merge checks (such as code style) on a pull request.
Home-page: http://pybee.org/beefore
Author: Russell Keith-Magee
Author-email: russell@keith-magee.com
License: New BSD
Keywords: lint,merge,dco
Platform: UNKNOWN
Classifier: Development Status :: 4 - Beta
Classifier: Intended Audience :: Developers
Classifier: License :: OSI Approved :: BSD License
Classifier: Operating System :: OS Independent
Classifier: Programming Language :: Python :: 3
Classifier: Programming Language :: Python :: 3.4
Classifier: Programming Language :: Python :: 3.5
Classifier: Programming Language :: Python :: 3.6
Classifier: Programming Language :: Python :: 3.7
Classifier: Topic :: Software Development
Classifier: Topic :: Utilities
Requires-Dist: gitpython
Requires-Dist: github3.py
Requires-Dist: PyYAML
Requires-Dist: flake8 (>=3.0.0b2)
